wordplay/__init__.py
wordplay/criteria.py
wordplay/dictionary.py
wordplay/utils.py
wordplay/data/sample_wordlist.dat
wordplay/data/scrabble_wordlist.dat
wordplay-1.0.0a4.dist-info/LICENSE.txt
wordplay-1.0.0a4.dist-info/METADATA
wordplay-1.0.0a4.dist-info/RECORD
wordplay-1.0.0a4.dist-info/WHEEL
wordplay-1.0.0a4.dist-info/top_level.txt
